capture_devices/__init__.py
capture_devices/capture_devices.py
capture_devices/utils_capture/__init__.py
capture_devices/utils_capture/utils.py
capture_devices-4.2.dist-info/LICENSE
capture_devices-4.2.dist-info/METADATA
capture_devices-4.2.dist-info/WHEEL
capture_devices-4.2.dist-info/top_level.txt
capture_devices-4.2.dist-info/RECORD
